drapi/__init__.py
drapi/code/__init__.py
drapi/code/drapi/__init__.py
drapi/code/drapi/classes.py
drapi/code/drapi/cli_parsers.py
drapi/code/drapi/compareGroups.py
drapi/code/drapi/deIdentificationFunctions.py
drapi/code/drapi/drapi.py
drapi/code/drapi/expandColumn.py
drapi/code/drapi/gather_files.py
drapi/code/drapi/getPersonIDs.py
drapi/code/drapi/makeListOfDates.py
drapi/code/drapi/makeSymLinks.py
drapi/code/drapi/modifyTSV.py
drapi/code/drapi/parseAliasArguments.py
drapi/code/drapi/prep_for_text_deidentification.py
drapi/code/drapi/replace_text.py
drapi/code/drapi/searchFolders.py
drapi/code/drapi/sql.py
drapi/code/drapi/stats.py
drapi/code/drapi/uploadData.py
drapi/code/drapi/c2s/__init__.py
drapi/code/drapi/c2s/c2s.py
drapi/code/drapi/constants/__init__.py
drapi/code/drapi/constants/constants.py
drapi/code/drapi/constants/phiValues.py
drapi/code/drapi/constants/phiVariables.py
drapi/code/drapi/constants/variableAliases.py
drapi/code/drapi/convertColumns/hash.py
drapi/code/drapi/deIdentificationSuiteFuncs0/__init__.py
drapi/code/drapi/deIdentificationSuiteFuncs0/common.py
drapi/code/drapi/deIdentificationSuiteFuncs0/concatenateMaps.py
drapi/code/drapi/deIdentificationSuiteFuncs0/convertColumns.py
drapi/code/drapi/deIdentificationSuiteFuncs0/dataQualityTest.py
drapi/code/drapi/deIdentificationSuiteFuncs0/deIdentify.py
drapi/code/drapi/deIdentificationSuiteFuncs0/deleteColumns.py
drapi/code/drapi/deIdentificationSuiteFuncs0/gatherFiles.py
drapi/code/drapi/deIdentificationSuiteFuncs0/getIDValues.py
drapi/code/drapi/deIdentificationSuiteFuncs0/getProjectColumns.py
drapi/code/drapi/deIdentificationSuiteFuncs0/makeMapsFromOthers.py
drapi/code/drapi/deIdentificationSuiteFuncs0/makeMapsFromScratch.py
drapi/code/drapi/deIdentificationSuiteFuncs0/makePersonIDMap.py
drapi/code/drapi/getData/getData.py
drapi/code/drapi/getData/getData_inner.py
drapi/code/drapi/getData/getData_outer.py
drapi/code/drapi/idealist/__init__.py
drapi/code/drapi/idealist/getEncountersMap.py
drapi_lemur-1.0.49.dist-info/METADATA
drapi_lemur-1.0.49.dist-info/WHEEL
drapi_lemur-1.0.49.dist-info/top_level.txt
drapi_lemur-1.0.49.dist-info/RECORD
