Metadata-Version: 2.4
Name: drapi-lemur
Version: 1.0.49
Summary: Data Request API for the Integrated Data Repository Research Services of University of Florida.
Home-page: https://github.com/ChemGuy88/hermanCode/archive/refs/tags/v1.0.0.tar.gz
Author: Herman Autore
Author-email: hf.autore+drapi@gmail.com
Keywords: CTSI,Clinical and Translational Science Institute,IDR,Integrated Data Repository,Integrated Data Repository Research Services,ODSRI,Office of Data Science and Research Implementation,Shands,Sloth 🦥,UF,UF Health,UFHealth,University of Florida
Dynamic: author
Dynamic: author-email
Dynamic: description
Dynamic: home-page
Dynamic: keywords
Dynamic: summary
